cfl_data_utils/__init__.py
cfl_data_utils/database/__init__.py
cfl_data_utils/database/_database.py
cfl_data_utils/database/postgresql_manager.py
cfl_data_utils/database/rds_manager.py
cfl_data_utils/references/__init__.py
cfl_data_utils/references/_type_tests.py
cfl_data_utils/references/constants.py
cfl_data_utils/services/__init__.py
cfl_data_utils/services/services.py
cfl_data_utils/utils/__init__.py
cfl_data_utils/utils/bytes_io_wrapper.py
cfl_data_utils/utils/dict_to_object.py
cfl_data_utils/utils/utils.py
cfl_data_utils-0.13.1.dist-info/LICENSE
cfl_data_utils-0.13.1.dist-info/METADATA
cfl_data_utils-0.13.1.dist-info/WHEEL
cfl_data_utils-0.13.1.dist-info/top_level.txt
cfl_data_utils-0.13.1.dist-info/RECORD
