Metadata-Version: 2.1
Name: cfl-data-utils
Version: 0.13.1
Summary: Utilities for the Data and Analytics team at Chetwood Financial
Home-page: https://github.com/chetwoodfinancial/data-utilities
Author: Will Garside
Author-email: will@chetwood.co
License: UNKNOWN
Platform: UNKNOWN
Classifier: Programming Language :: Python :: 3
Classifier: License :: OSI Approved :: MIT License
Classifier: Operating System :: OS Independent
Requires-Dist: sshtunnel
Requires-Dist: pymysql
Requires-Dist: psycopg2-binary
Requires-Dist: requests
Requires-Dist: blessings
Requires-Dist: pandas
Requires-Dist: sqlalchemy
Requires-Dist: boto3
